cytopath/__init__.py
cytopath/anndata.py
cytopath/markov_chain_sampler.py
cytopath/plotting.py
cytopath/scvelo.py
cytopath/trajectory_inference.py
cytopath/utils.py
cytopath/plotting_functions/__init__.py
cytopath/plotting_functions/plot_alignment.py
cytopath/plotting_functions/plot_radial_heatmap.py
cytopath/plotting_functions/plot_sampling.py
cytopath/trajectory_estimation/__init__.py
cytopath/trajectory_estimation/cyto_path.py
cytopath/trajectory_estimation/cytopath_merger.py
cytopath/trajectory_estimation/sample_clustering.py
cytopath-0.1.9.dist-info/LICENSE
cytopath-0.1.9.dist-info/METADATA
cytopath-0.1.9.dist-info/WHEEL
cytopath-0.1.9.dist-info/top_level.txt
cytopath-0.1.9.dist-info/RECORD
