Metadata-Version: 2.1
Name: cytopath
Version: 0.1.9
Summary: Simulation based inference of differentiation trajectories from RNA velocity fields.
Home-page: https://github.com/aron0093/cytopath
Download-URL: https://github.com/aron0093/cytopath/archive/v_019.tar.gz
Author: Revant Gupta
Author-email: revant.gupta.93@gmail.com
License: BSD 3-Clause License
Keywords: Trajectory Inference,single-cell RNA sequencing,RNA velocity
Classifier: Development Status :: 4 - Beta
Classifier: Intended Audience :: Science/Research
Classifier: Topic :: Software Development :: Build Tools
Classifier: License :: OSI Approved :: BSD License
Classifier: Programming Language :: Python :: 3.7
Classifier: Programming Language :: Python :: 3.8
License-File: LICENSE
Requires-Dist: numpy (>=1.20.0)
Requires-Dist: scipy
Requires-Dist: anndata
Requires-Dist: scvelo (>=0.1.25)
Requires-Dist: joblib
Requires-Dist: fastdtw
Requires-Dist: hausdorff
Requires-Dist: tqdm
Requires-Dist: networkit
Requires-Dist: tabulate
Requires-Dist: numba
